fch/__init__.py
fch/__main__.py
fch/core/__init__.py
fch/core/datamanager.py
fch/core/mementodownloader.py
fch/core/timemapdownloader.py
fch/core/config/__init__.py
fch/core/config/configreader.py
fch/core/config/configwriter.py
fch/core/config/data/config.ini
fch/core/utils/__init__.py
fch/core/utils/constants.py
fch/core/utils/util_functions.py
fch/follower/__init__.py
fch/follower/followeranalysis.py
fch/follower/followercount.py
fch/follower/followerparser.py
fch-1.0.14.dist-info/LICENSE
fch-1.0.14.dist-info/METADATA
fch-1.0.14.dist-info/WHEEL
fch-1.0.14.dist-info/entry_points.txt
fch-1.0.14.dist-info/top_level.txt
fch-1.0.14.dist-info/RECORD
