Metadata-Version: 2.1
Name: fch
Version: 1.0.14
Summary: A Python library to find historical Twitter follower count using the web archives
Home-page: https://github.com/oduwsdl/FollowerCountHistory
Author: Mohammed Nauman Siddique
Author-email: msidd003@odu.edu
License: MIT
Platform: UNKNOWN
Classifier: Development Status :: 5 - Production/Stable
Classifier: Programming Language :: Python :: 3.5
Classifier: Programming Language :: Python :: 3.6
Classifier: License :: OSI Approved :: MIT License
Classifier: Topic :: Internet :: WWW/HTTP
Classifier: Topic :: System :: Archiving
Classifier: Topic :: System :: Archiving :: Backup
Provides: fch
Requires-Dist: warcio
Requires-Dist: requests
Requires-Dist: beautifulsoup4
